{
  "element": {
    "sourceTag": "container",
    "type": "custom",
    "children": [
      {
        "sourceTag": "text",
        "type": "custom",
        "children": [
          "SELECT MODE"
        ],
        "properties": {
          "fontSize": "20",
          "color": "#00ffff",
          "fontWeight": "bold",
          "textAlign": "center"
        },
        "dataUid": "uid-2"
      },
      {
        "sourceTag": "text",
        "type": "custom",
        "children": [
          "Classic"
        ],
        "properties": {
          "name": "btn-classic",
          "fontSize": "14",
          "color": "#00ffff",
          "backgroundColor": "#003333",
          "padding": "6",
          "borderRadius": "6",
          "borderWidth": "1",
          "borderColor": "#00ffff",
          "textAlign": "center",
          "width": "240",
          "cursor": "pointer"
        },
        "dataUid": "uid-3"
      },
      {
        "sourceTag": "text",
        "type": "custom",
        "children": [
          "Timed"
        ],
        "properties": {
          "name": "btn-timed",
          "fontSize": "14",
          "color": "#ff8800",
          "backgroundColor": "#221100",
          "padding": "6",
          "borderRadius": "6",
          "borderWidth": "1",
          "borderColor": "#ff8800",
          "textAlign": "center",
          "width": "240",
          "cursor": "pointer"
        },
        "dataUid": "uid-4"
      },
      {
        "sourceTag": "text",
        "type": "custom",
        "children": [
          "Daily Challenge"
        ],
        "properties": {
          "name": "btn-daily",
          "fontSize": "14",
          "color": "#ffff00",
          "backgroundColor": "#222200",
          "padding": "6",
          "borderRadius": "6",
          "borderWidth": "1",
          "borderColor": "#ffff00",
          "textAlign": "center",
          "width": "240",
          "cursor": "pointer"
        },
        "dataUid": "uid-5"
      },
      {
        "sourceTag": "text",
        "type": "custom",
        "children": [
          "Zen"
        ],
        "properties": {
          "name": "btn-zen",
          "fontSize": "14",
          "color": "#00ff88",
          "backgroundColor": "#002211",
          "padding": "6",
          "borderRadius": "6",
          "borderWidth": "1",
          "borderColor": "#00ff88",
          "textAlign": "center",
          "width": "240",
          "cursor": "pointer"
        },
        "dataUid": "uid-6"
      },
      {
        "sourceTag": "text",
        "type": "custom",
        "children": [
          "Speed"
        ],
        "properties": {
          "name": "btn-speed",
          "fontSize": "14",
          "color": "#ff44ff",
          "backgroundColor": "#220022",
          "padding": "6",
          "borderRadius": "6",
          "borderWidth": "1",
          "borderColor": "#ff44ff",
          "textAlign": "center",
          "width": "240",
          "cursor": "pointer"
        },
        "dataUid": "uid-7"
      },
      {
        "sourceTag": "text",
        "type": "custom",
        "children": [
          "Practice"
        ],
        "properties": {
          "name": "btn-practice",
          "fontSize": "14",
          "color": "#aaaaaa",
          "backgroundColor": "#111111",
          "padding": "6",
          "borderRadius": "6",
          "borderWidth": "1",
          "borderColor": "#444444",
          "textAlign": "center",
          "width": "240",
          "cursor": "pointer"
        },
        "dataUid": "uid-8"
      },
      {
        "sourceTag": "text",
        "type": "custom",
        "children": [
          "BACK"
        ],
        "properties": {
          "name": "btn-back",
          "fontSize": "12",
          "color": "#888888",
          "backgroundColor": "#111111",
          "padding": "4",
          "borderRadius": "4",
          "textAlign": "center",
          "width": "120",
          "cursor": "pointer",
          "marginTop": "4"
        },
        "dataUid": "uid-9"
      }
    ],
    "properties": {
      "name": "root",
      "display": "none",
      "flexDirection": "column",
      "alignItems": "center",
      "padding": "16",
      "backgroundColor": "#001a1a",
      "borderRadius": "12",
      "borderWidth": "2",
      "borderColor": "#00ffff",
      "width": "320",
      "gap": "6"
    },
    "dataUid": "uid-1"
  },
  "classes": {},
  "ranges": {
    "uid-1": {
      "start": {
        "line": 0,
        "column": 0
      },
      "end": {
        "line": 9,
        "column": 12
      }
    },
    "uid-2": {
      "start": {
        "line": 1,
        "column": 2
      },
      "end": {
        "line": 1,
        "column": 96
      }
    },
    "uid-3": {
      "start": {
        "line": 2,
        "column": 2
      },
      "end": {
        "line": 2,
        "column": 218
      }
    },
    "uid-4": {
      "start": {
        "line": 3,
        "column": 2
      },
      "end": {
        "line": 3,
        "column": 214
      }
    },
    "uid-5": {
      "start": {
        "line": 4,
        "column": 2
      },
      "end": {
        "line": 4,
        "column": 224
      }
    },
    "uid-6": {
      "start": {
        "line": 5,
        "column": 2
      },
      "end": {
        "line": 5,
        "column": 210
      }
    },
    "uid-7": {
      "start": {
        "line": 6,
        "column": 2
      },
      "end": {
        "line": 6,
        "column": 214
      }
    },
    "uid-8": {
      "start": {
        "line": 7,
        "column": 2
      },
      "end": {
        "line": 7,
        "column": 220
      }
    },
    "uid-9": {
      "start": {
        "line": 8,
        "column": 2
      },
      "end": {
        "line": 8,
        "column": 187
      }
    }
  }
}